{"folders":[],"files":[{"basename":"mcq-2023#-s3-01-correction.csv","path":"S3/MCQs/2023%23/mcq-2023%23-s3-01-correction.csv"},{"mcq":true,"basename":"mcq-2023#-s3-01-mcq.json","path":"S3/MCQs/2023%23/mcq-2023%23-s3-01-mcq.json"},{"embed":true,"basename":"mcq-2023#-s3-01.pdf","path":"S3/MCQs/2023%23/mcq-2023%23-s3-01.pdf"},{"basename":"mcq-2023#-s3-02-correction.csv","path":"S3/MCQs/2023%23/mcq-2023%23-s3-02-correction.csv"},{"mcq":true,"basename":"mcq-2023#-s3-02-mcq.json","path":"S3/MCQs/2023%23/mcq-2023%23-s3-02-mcq.json"},{"embed":true,"basename":"mcq-2023#-s3-02.pdf","path":"S3/MCQs/2023%23/mcq-2023%23-s3-02.pdf"}]}